payman_zarinpal-1.0.0.dist-info/licenses/LICENSE
zarinpal/__init__.py
zarinpal/gateway.py
zarinpal/adapters/__init__.py
zarinpal/adapters/base_url_builder.py
zarinpal/adapters/error_mapper.py
zarinpal/adapters/http_client.py
zarinpal/enums/__init__.py
zarinpal/enums/status.py
zarinpal/exception/__init__.py
zarinpal/exception/zarinpal_errors.py
zarinpal/methods/__init__.py
zarinpal/methods/get_unverified_payments.py
zarinpal/methods/payment_initiator.py
zarinpal/methods/redirector.py
zarinpal/methods/reverse_transaction.py
zarinpal/methods/verify_payment.py
zarinpal/models/__init__.py
zarinpal/models/callback.py
zarinpal/models/payment_request.py
zarinpal/models/payment_response.py
zarinpal/models/reverse_request.py
zarinpal/models/reverse_response.py
zarinpal/models/unverified_payments.py
zarinpal/models/verify_request.py
zarinpal/models/verify_response.py
zarinpal/models/wage.py
payman_zarinpal-1.0.0.dist-info/METADATA
payman_zarinpal-1.0.0.dist-info/WHEEL
payman_zarinpal-1.0.0.dist-info/top_level.txt
payman_zarinpal-1.0.0.dist-info/RECORD
