Metadata-Version: 2.4
Name: payman-zarinpal
Version: 1.0.0
Summary: ZarinPal payment gateway plugin for Payman
Author-email: AmirAli Irvani <irvaniamirali.dev@gmail.com>
License: MIT
Keywords: payment,gateway,zarinpal,payman,plugin
Classifier: Programming Language :: Python :: 3
Classifier: License :: OSI Approved :: MIT License
Classifier: Operating System :: OS Independent
Requires-Python: >=3.13
License-File: LICENSE
Requires-Dist: payman>=3.0.3
Dynamic: license-file
